Activities/Activity4/Activity4.v
/* Activity 4: PC/Adder/Memory and Jump/ Control
January 25, 2018
*/
//`include "mips.h"

//////////// PC //////////////
module pc(input clock, input [31:0] nextPC, output reg[31:0] currPC);

initial
begin
	currPC = 32'h00400000;
end

always @(posedge clock) begin
	currPC <= nextPC;
end
endmodule


///////////// adder /////////////
module add4 (input [31:0] currPC, output [31:0] PCplus4);
	assign PCplus4 = currPC + 4;
endmodule


///////////// Memory /////////////
module memory(input [31:0] currPC, output reg[31:0] inst); 
	reg [31:0] mem[30'h00100000:30'h00100003];	

	initial
	begin
		$readmemh("Jumps.in", mem);
	end

	always @(currPC) 
	begin
		inst = mem[currPC[31:2]];
		if (inst == 0) begin
			$finish;
		end
	end
endmodule

/////////////// Control /////////////
module control(input [31:0] inst, output reg jumpOut);

	initial
	begin
		jumpOut = 0;
	end
	always @(*) begin
		case(inst[31:26]) 
			6'h2: jumpOut =1;
			default: jumpOut = 0;
		endcase; 
	end

endmodule


/////////////// Calculate Jump Address
module calculateJumpAddress(input [31:0] PCplus4, input [31:0] inst, output wire [31:0] jumpAddr);
	assign jumpAddr = {PCplus4[31:28], inst[25:0] << 2};
endmodule
////////////// mux 2-to-1 ///////////
module mux2to1Bit(input jumpOut, input [31:0] jumpAddr, input [31:0] PCplus4, output reg [31:0] nextPC);
	always @(*)
	begin 
		if (jumpOut == 1)
			nextPC = jumpAddr;
		else
			nextPC = PCplus4;
	end

endmodule
//////////// TestBench /////////////
module testbench;
wire [31:0] nextPC;
wire [31:0] currPC;
wire [31:0] inst;
wire [31:0] jumpAddr;
wire [31:0] PCplus4;
wire jumpOut;


reg clock = 0;

pc testPC(clock, nextPC, currPC);
add4 adder(currPC, PCplus4);
memory mem(currPC, inst);
//calculateJumpAddress jumper(inst, PCplus4, jumpAddr);
assign jumpAddr = {PCplus4[31:28], inst[25:0] << 2};
control ctrl(inst, jumpOut);
mux2to1Bit mux(jumpOut,jumpAddr,PCplus4, nextPC);

always begin
	#1 clock = ~clock;
end 

initial
	begin
    	$dumpfile("testbench.vcd");
    	$dumpvars(0,testbench);

    	$monitor($time, "in %m, currPC %08x, nextPC = %08x, inst =%08x, jumpAddr =%08x, PCplus4 =%08x, jumpOut=%01x", currPC, nextPC, inst, jumpAddr, PCplus4, jumpOut);
    	#1000
		$finish;
	end
endmodule

Activities/Activity4/testbench.vcd
$date
	Thu Feb  1 13:28:50 2018
$end
$version
	Icarus Verilog
$end
$timescale
	1s
$end
$scope module testbench $end
$var wire 32 ! nextPC [31:0] $end
$var wire 1 " jumpOut $end
$var wire 32 # jumpAddr [31:0] $end
$var wire 32 $ inst [31:0] $end
$var wire 32 % currPC [31:0] $end
$var wire 32 & PCplus4 [31:0] $end
$var reg 1 ' clock $end
$scope module adder $end
$var wire 32 ( currPC [31:0] $end
$var wire 32 ) PCplus4 [31:0] $end
$upscope $end
$scope module ctrl $end
$var wire 32 * inst [31:0] $end
$var reg 1 " jumpOut $end
$upscope $end
$scope module mem $end
$var wire 32 + currPC [31:0] $end
$var reg 32 , inst [31:0] $end
$upscope $end
$scope module mux $end
$var wire 32 - PCplus4 [31:0] $end
$var wire 32 . jumpAddr [31:0] $end
$var wire 1 " jumpOut $end
$var reg 32 / nextPC [31:0] $end
$upscope $end
$scope module testPC $end
$var wire 1 ' clock $end
$var wire 32 0 nextPC [31:0] $end
$var reg 32 1 currPC [31:0] $end
$upscope $end
$upscope $end
$enddefinitions $end
#0
$dumpvars
b10000000000000000000000 1
b10000000000000000000100 0
b10000000000000000000100 /
b10000000000000010000 .
b10000000000000000000100 -
b100100000000100000000000000100 ,
b10000000000000000000000 +
b100100000000100000000000000100 *
b10000000000000000000100 )
b10000000000000000000000 (
0'
b10000000000000000000100 &
b10000000000000000000000 %
b100100000000100000000000000100 $
b10000000000000010000 #
0"
b10000000000000000000100 !
$end
#1
b110000 #
b110000 .
b10000000000000000001000 !
b10000000000000000001000 /
b10000000000000000001000 0
b1100 $
b1100 *
b1100 ,
b10000000000000000001000 &
b10000000000000000001000 )
b10000000000000000001000 -
b10000000000000000000100 %
b10000000000000000000100 (
b10000000000000000000100 +
b10000000000000000000100 1
1'
#2
0'
#3
b11100000000000000000100000 #
b11100000000000000000100000 .
b10000000000000000001100 !
b10000000000000000001100 /
b10000000000000000001100 0
b11111000000000000000001000 $
b11111000000000000000001000 *
b11111000000000000000001000 ,
b10000000000000000001100 &
b10000000000000000001100 )
b10000000000000000001100 -
b10000000000000000001000 %
b10000000000000000001000 (
b10000000000000000001000 +
b10000000000000000001000 1
1'
#4
0'
#5
b10000000000000000000000 #
b10000000000000000000000 .
1"
b10000000000000000000000 !
b10000000000000000000000 /
b10000000000000000000000 0
b1000000100000000000000000000 $
b1000000100000000000000000000 *
b1000000100000000000000000000 ,
b10000000000000000010000 &
b10000000000000000010000 )
b10000000000000000010000 -
b10000000000000000001100 %
b10000000000000000001100 (
b10000000000000000001100 +
b10000000000000000001100 1
1'
#6
0'
#7
b10000000000000010000 #
b10000000000000010000 .
b10000000000000000000100 !
b10000000000000000000100 /
b10000000000000000000100 0
0"
b100100000000100000000000000100 $
b100100000000100000000000000100 *
b100100000000100000000000000100 ,
b10000000000000000000100 &
b10000000000000000000100 )
b10000000000000000000100 -
b10000000000000000000000 %
b10000000000000000000000 (
b10000000000000000000000 +
b10000000000000000000000 1
1'
#8
0'
#9
b110000 #
b110000 .
b10000000000000000001000 !
b10000000000000000001000 /
b10000000000000000001000 0
b1100 $
b1100 *
b1100 ,
b10000000000000000001000 &
b10000000000000000001000 )
b10000000000000000001000 -
b10000000000000000000100 %
b10000000000000000000100 (
b10000000000000000000100 +
b10000000000000000000100 1
1'
#10
0'
#11
b11100000000000000000100000 #
b11100000000000000000100000 .
b10000000000000000001100 !
b10000000000000000001100 /
b10000000000000000001100 0
b11111000000000000000001000 $
b11111000000000000000001000 *
b11111000000000000000001000 ,
b10000000000000000001100 &
b10000000000000000001100 )
b10000000000000000001100 -
b10000000000000000001000 %
b10000000000000000001000 (
b10000000000000000001000 +
b10000000000000000001000 1
1'
#12
0'
#13
b10000000000000000000000 #
b10000000000000000000000 .
1"
b10000000000000000000000 !
b10000000000000000000000 /
b10000000000000000000000 0
b1000000100000000000000000000 $
b1000000100000000000000000000 *
b1000000100000000000000000000 ,
b10000000000000000010000 &
b10000000000000000010000 )
b10000000000000000010000 -
b10000000000000000001100 %
b10000000000000000001100 (
b10000000000000000001100 +
b10000000000000000001100 1
1'
#14
0'
#15
b10000000000000010000 #
b10000000000000010000 .
b10000000000000000000100 !
b10000000000000000000100 /
b10000000000000000000100 0
0"
b100100000000100000000000000100 $
b100100000000100000000000000100 *
b100100000000100000000000000100 ,
b10000000000000000000100 &
b10000000000000000000100 )
b10000000000000000000100 -
b10000000000000000000000 %
b10000000000000000000000 (
b10000000000000000000000 +
b10000000000000000000000 1
1'
#16
0'
#17
b110000 #
b110000 .
b10000000000000000001000 !
b10000000000000000001000 /
b10000000000000000001000 0
b1100 $
b1100 *
b1100 ,
b10000000000000000001000 &
b10000000000000000001000 )
b10000000000000000001000 -
b10000000000000000000100 %
b10000000000000000000100 (
b10000000000000000000100 +
b10000000000000000000100 1
1'
#18
0'
#19
b11100000000000000000100000 #
b11100000000000000000100000 .
b10000000000000000001100 !
b10000000000000000001100 /
b10000000000000000001100 0
b11111000000000000000001000 $
b11111000000000000000001000 *
b11111000000000000000001000 ,
b10000000000000000001100 &
b10000000000000000001100 )
b10000000000000000001100 -
b10000000000000000001000 %
b10000000000000000001000 (
b10000000000000000001000 +
b10000000000000000001000 1
1'
#20
0'
#21
b10000000000000000000000 #
b10000000000000000000000 .
1"
b10000000000000000000000 !
b10000000000000000000000 /
b10000000000000000000000 0
b1000000100000000000000000000 $
b1000000100000000000000000000 *
b1000000100000000000000000000 ,
b10000000000000000010000 &
b10000000000000000010000 )
b10000000000000000010000 -
b10000000000000000001100 %
b10000000000000000001100 (
b10000000000000000001100 +
b10000000000000000001100 1
1'
#22
0'
#23
b10000000000000010000 #
b10000000000000010000 .
b10000000000000000000100 !
b10000000000000000000100 /
b10000000000000000000100 0
0"
b100100000000100000000000000100 $
b100100000000100000000000000100 *
b100100000000100000000000000100 ,
b10000000000000000000100 &
b10000000000000000000100 )
b10000000000000000000100 -
b10000000000000000000000 %
b10000000000000000000000 (
b10000000000000000000000 +
b10000000000000000000000 1
1'
#24
0'
#25
b110000 #
b110000 .
b10000000000000000001000 !
b10000000000000000001000 /
b10000000000000000001000 0
b1100 $
b1100 *
b1100 ,
b10000000000000000001000 &
b10000000000000000001000 )
b10000000000000000001000 -
b10000000000000000000100 %
b10000000000000000000100 (
b10000000000000000000100 +
b10000000000000000000100 1
1'
#26
0'
#27
b11100000000000000000100000 #
b11100000000000000000100000 .
b10000000000000000001100 !
b10000000000000000001100 /
b10000000000000000001100 0
b11111000000000000000001000 $
b11111000000000000000001000 *
b11111000000000000000001000 ,
b10000000000000000001100 &
b10000000000000000001100 )
b10000000000000000001100 -
b10000000000000000001000 %
b10000000000000000001000 (
b10000000000000000001000 +
b10000000000000000001000 1
1'
#28
0'
#29
b10000000000000000000000 #
b10000000000000000000000 .
1"
b10000000000000000000000 !
b10000000000000000000000 /
b10000000000000000000000 0
b1000000100000000000000000000 $
b1000000100000000000000000000 *
b1000000100000000000000000000 ,
b10000000000000000010000 &
b10000000000000000010000 )
b10000000000000000010000 -
b10000000000000000001100 %
b10000000000000000001100 (
b10000000000000000001100 +
b10000000000000000001100 1
1'
#30
0'
#31
b10000000000000010000 #
b10000000000000010000 .
b10000000000000000000100 !
b10000000000000000000100 /
b10000000000000000000100 0
0"
b100100000000100000000000000100 $
b100100000000100000000000000100 *
b100100000000100000000000000100 ,
b10000000000000000000100 &
b10000000000000000000100 )
b10000000000000000000100 -
b10000000000000000000000 %
b10000000000000000000000 (
b10000000000000000000000 +
b10000000000000000000000 1
1'
#32
0'
#33
b110000 #
b110000 .
b10000000000000000001000 !
b10000000000000000001000 /
b10000000000000000001000 0
b1100 $
b1100 *
b1100 ,
b10000000000000000001000 &
b10000000000000000001000 )
b10000000000000000001000 -
b10000000000000000000100 %
b10000000000000000000100 (
b10000000000000000000100 +
b10000000000000000000100 1
1'
#34
0'
#35
b11100000000000000000100000 #
b11100000000000000000100000 .
b10000000000000000001100 !
b10000000000000000001100 /
b10000000000000000001100 0
b11111000000000000000001000 $
b11111000000000000000001000 *
b11111000000000000000001000 ,
b10000000000000000001100 &
b10000000000000000001100 )
b10000000000000000001100 -
b10000000000000000001000 %
b10000000000000000001000 (
b10000000000000000001000 +
b10000000000000000001000 1
1'
#36
0'
#37
b10000000000000000000000 #
b10000000000000000000000 .
1"
b10000000000000000000000 !
b10000000000000000000000 /
b10000000000000000000000 0
b1000000100000000000000000000 $
b1000000100000000000000000000 *
b1000000100000000000000000000 ,
b10000000000000000010000 &
b10000000000000000010000 )
b10000000000000000010000 -
b10000000000000000001100 %
b10000000000000000001100 (
b10000000000000000001100 +
b10000000000000000001100 1
1'
#38
0'
#39
b10000000000000010000 #
b10000000000000010000 .
b10000000000000000000100 !
b10000000000000000000100 /
b10000000000000000000100 0
0"
b100100000000100000000000000100 $
b100100000000100000000000000100 *
b100100000000100000000000000100 ,
b10000000000000000000100 &
b10000000000000000000100 )
b10000000000000000000100 -
b10000000000000000000000 %
b10000000000000000000000 (
b10000000000000000000000 +
b10000000000000000000000 1
1'
#40
0'
#41
b110000 #
b110000 .
b10000000000000000001000 !
b10000000000000000001000 /
b10000000000000000001000 0
b1100 $
b1100 *
b1100 ,
b10000000000000000001000 &
b10000000000000000001000 )
b10000000000000000001000 -
b10000000000000000000100 %
b10000000000000000000100 (
b10000000000000000000100 +
b10000000000000000000100 1
1'
#42
0'
#43
b11100000000000000000100000 #
b11100000000000000000100000 .
b10000000000000000001100 !
b10000000000000000001100 /
b10000000000000000001100 0
b11111000000000000000001000 $
b11111000000000000000001000 *
b11111000000000000000001000 ,
b10000000000000000001100 &
b10000000000000000001100 )
b10000000000000000001100 -
b10000000000000000001000 %
b10000000000000000001000 (
b10000000000000000001000 +
b10000000000000000001000 1
1'
#44
0'
#45
b10000000000000000000000 #
b10000000000000000000000 .
1"
b10000000000000000000000 !
b10000000000000000000000 /
b10000000000000000000000 0
b1000000100000000000000000000 $
b1000000100000000000000000000 *
b1000000100000000000000000000 ,
b10000000000000000010000 &
b10000000000000000010000 )
b10000000000000000010000 -
b10000000000000000001100 %
b10000000000000000001100 (
b10000000000000000001100 +
b10000000000000000001100 1
1'
#46
0'
#47
b10000000000000010000 #
b10000000000000010000 .
b10000000000000000000100 !
b10000000000000000000100 /
b10000000000000000000100 0
0"
b100100000000100000000000000100 $
b100100000000100000000000000100 *
b100100000000100000000000000100 ,
b10000000000000000000100 &
b10000000000000000000100 )
b10000000000000000000100 -
b10000000000000000000000 %
b10000000000000000000000 (
b10000000000000000000000 +
b10000000000000000000000 1
1'
#48
0'
#49
b110000 #
b110000 .
b10000000000000000001000 !
b10000000000000000001000 /
b10000000000000000001000 0
b1100 $
b1100 *
b1100 ,
b10000000000000000001000 &
b10000000000000000001000 )
b10000000000000000001000 -
b10000000000000000000100 %
b10000000000000000000100 (
b10000000000000000000100 +
b10000000000000000000100 1
1'
#50
0'
#51
b11100000000000000000100000 #
b11100000000000000000100000 .
b10000000000000000001100 !
b10000000000000000001100 /
b10000000000000000001100 0
b11111000000000000000001000 $
b11111000000000000000001000 *
b11111000000000000000001000 ,
b10000000000000000001100 &
b10000000000000000001100 )
b10000000000000000001100 -
b10000000000000000001000 %
b10000000000000000001000 (
b10000000000000000001000 +
b10000000000000000001000 1
1'
#52
0'
#53
b10000000000000000000000 #
b10000000000000000000000 .
1"
b10000000000000000000000 !
b10000000000000000000000 /
b10000000000000000000000 0
b1000000100000000000000000000 $
b1000000100000000000000000000 *
b1000000100000000000000000000 ,
b10000000000000000010000 &
b10000000000000000010000 )
b10000000000000000010000 -
b10000000000000000001100 %
b10000000000000000001100 (
b10000000000000000001100 +
b10000000000000000001100 1
1'
#54
0'
#55
b10000000000000010000 #
b10000000000000010000 .
b10000000000000000000100 !
b10000000000000000000100 /
b10000000000000000000100 0
0"
b100100000000100000000000000100 $
b100100000000100000000000000100 *
b100100000000100000000000000100 ,
b10000000000000000000100 &
b10000000000000000000100 )
b10000000000000000000100 -
b10000000000000000000000 %
b10000000000000000000000 (
b10000000000000000000000 +
b10000000000000000000000 1
1'
#56
0'
#57
b110000 #
b110000 .
b10000000000000000001000 !
b10000000000000000001000 /
b10000000000000000001000 0
b1100 $
b1100 *
b1100 ,
b10000000000000000001000 &
b10000000000000000001000 )
b10000000000000000001000 -
b10000000000000000000100 %
b10000000000000000000100 (
b10000000000000000000100 +
b10000000000000000000100 1
1'
#58
0'
#59
b11100000000000000000100000 #
b11100000000000000000100000 .
b10000000000000000001100 !
b10000000000000000001100 /
b10000000000000000001100 0
b11111000000000000000001000 $
b11111000000000000000001000 *
b11111000000000000000001000 ,
b10000000000000000001100 &
b10000000000000000001100 )
b10000000000000000001100 -
b10000000000000000001000 %
b10000000000000000001000 (
b10000000000000000001000 +
b10000000000000000001000 1
1'
#60
0'
#61
b10000000000000000000000 #
b10000000000000000000000 .
1"
b10000000000000000000000 !
b10000000000000000000000 /
b10000000000000000000000 0
b1000000100000000000000000000 $
b1000000100000000000000000000 *
b1000000100000000000000000000 ,
b10000000000000000010000 &
b10000000000000000010000 )
b10000000000000000010000 -
b10000000000000000001100 %
b10000000000000000001100 (
b10000000000000000001100 +
b10000000000000000001100 1
1'
#62
0'
#63
b10000000000000010000 #
b10000000000000010000 .
b10000000000000000000100 !
b10000000000000000000100 /
b10000000000000000000100 0
0"
b100100000000100000000000000100 $
b100100000000100000000000000100 *
b100100000000100000000000000100 ,
b10000000000000000000100 &
b10000000000000000000100 )
b10000000000000000000100 -
b10000000000000000000000 %
b10000000000000000000000 (
b10000000000000000000000 +
b10000000000000000000000 1
1'
#64
0'
#65
b110000 #
b110000 .
b10000000000000000001000 !
b10000000000000000001000 /
b10000000000000000001000 0
b1100 $
b1100 *
b1100 ,
b10000000000000000001000 &
b10000000000000000001000 )
b10000000000000000001000 -
b10000000000000000000100 %
b10000000000000000000100 (
b10000000000000000000100 +
b10000000000000000000100 1
1'
#66
0'
#67
b11100000000000000000100000 #
b11100000000000000000100000 .
b10000000000000000001100 !
b10000000000000000001100 /
b10000000000000000001100 0
b11111000000000000000001000 $
b11111000000000000000001000 *
b11111000000000000000001000 ,
b10000000000000000001100 &
b10000000000000000001100 )
b10000000000000000001100 -
b10000000000000000001000 %
b10000000000000000001000 (
b10000000000000000001000 +
b10000000000000000001000 1
1'
#68
0'
#69
b10000000000000000000000 #
b10000000000000000000000 .
1"
b10000000000000000000000 !
b10000000000000000000000 /
b10000000000000000000000 0
b1000000100000000000000000000 $
b1000000100000000000000000000 *
b1000000100000000000000000000 ,
b10000000000000000010000 &
b10000000000000000010000 )
b10000000000000000010000 -
b10000000000000000001100 %
b10000000000000000001100 (
b10000000000000000001100 +
b10000000000000000001100 1
1'
#70
0'
#71
b10000000000000010000 #
b10000000000000010000 .
b10000000000000000000100 !
b10000000000000000000100 /
b10000000000000000000100 0
0"
b100100000000100000000000000100 $
b100100000000100000000000000100 *
b100100000000100000000000000100 ,
b10000000000000000000100 &
b10000000000000000000100 )
b10000000000000000000100 -
b10000000000000000000000 %
b10000000000000000000000 (
b10000000000000000000000 +
b10000000000000000000000 1
1'
#72
0'
#73
b110000 #
b110000 .
b10000000000000000001000 !
b10000000000000000001000 /
b10000000000000000001000 0
b1100 $
b1100 *
b1100 ,
b10000000000000000001000 &
b10000000000000000001000 )
b10000000000000000001000 -
b10000000000000000000100 %
b10000000000000000000100 (
b10000000000000000000100 +
b10000000000000000000100 1
1'
#74
0'
#75
b11100000000000000000100000 #
b11100000000000000000100000 .
b10000000000000000001100 !
b10000000000000000001100 /
b10000000000000000001100 0
b11111000000000000000001000 $
b11111000000000000000001000 *
b11111000000000000000001000 ,
b10000000000000000001100 &
b10000000000000000001100 )
b10000000000000000001100 -
b10000000000000000001000 %
b10000000000000000001000 (
b10000000000000000001000 +
b10000000000000000001000 1
1'
#76
0'
#77
b10000000000000000000000 #
b10000000000000000000000 .
1"
b10000000000000000000000 !
b10000000000000000000000 /
b10000000000000000000000 0
b1000000100000000000000000000 $
b1000000100000000000000000000 *
b1000000100000000000000000000 ,
b10000000000000000010000 &
b10000000000000000010000 )
b10000000000000000010000 -
b10000000000000000001100 %
b10000000000000000001100 (
b10000000000000000001100 +
b10000000000000000001100 1
1'
#78
0'
#79
b10000000000000010000 #
b10000000000000010000 .
b10000000000000000000100 !
b10000000000000000000100 /
b10000000000000000000100 0
0"
b100100000000100000000000000100 $
b100100000000100000000000000100 *
b100100000000100000000000000100 ,
b10000000000000000000100 &
b10000000000000000000100 )
b10000000000000000000100 -
b10000000000000000000000 %
b10000000000000000000000 (
b10000000000000000000000 +
b10000000000000000000000 1
1'
#80
0'
#81
b110000 #
b110000 .
b10000000000000000001000 !
b10000000000000000001000 /
b10000000000000000001000 0
b1100 $
b1100 *
b1100 ,
b10000000000000000001000 &
b10000000000000000001000 )
b10000000000000000001000 -
b10000000000000000000100 %
b10000000000000000000100 (
b10000000000000000000100 +
b10000000000000000000100 1
1'
#82
0'
#83
b11100000000000000000100000 #
b11100000000000000000100000 .
b10000000000000000001100 !
b10000000000000000001100 /
b10000000000000000001100 0
b11111000000000000000001000 $
b11111000000000000000001000 *
b11111000000000000000001000 ,
b10000000000000000001100 &
b10000000000000000001100 )
b10000000000000000001100 -
b10000000000000000001000 %
b10000000000000000001000 (
b10000000000000000001000 +
b10000000000000000001000 1
1'
#84
0'
#85
b10000000000000000000000 #
b10000000000000000000000 .
1"
b10000000000000000000000 !
b10000000000000000000000 /
b10000000000000000000000 0
b1000000100000000000000000000 $
b1000000100000000000000000000 *
b1000000100000000000000000000 ,
b10000000000000000010000 &
b10000000000000000010000 )
b10000000000000000010000 -
b10000000000000000001100 %
b10000000000000000001100 (
b10000000000000000001100 +
b10000000000000000001100 1
1'
#86
0'
#87
b10000000000000010000 #
b10000000000000010000 .
b10000000000000000000100 !
b10000000000000000000100 /
b10000000000000000000100 0
0"
b100100000000100000000000000100 $
b100100000000100000000000000100 *
b100100000000100000000000000100 ,
b10000000000000000000100 &
b10000000000000000000100 )
b10000000000000000000100 -
b10000000000000000000000 %
b10000000000000000000000 (
b10000000000000000000000 +
b10000000000000000000000 1
1'
#88
0'
#89
b110000 #
b110000 .
b10000000000000000001000 !
b10000000000000000001000 /
b10000000000000000001000 0
b1100 $
b1100 *
b1100 ,
b10000000000000000001000 &
b10000000000000000001000 )
b10000000000000000001000 -
b10000000000000000000100 %
b10000000000000000000100 (
b10000000000000000000100 +
b10000000000000000000100 1
1'
#90
0'
#91
b11100000000000000000100000 #
b11100000000000000000100000 .
b10000000000000000001100 !
b10000000000000000001100 /
b10000000000000000001100 0
b11111000000000000000001000 $
b11111000000000000000001000 *
b11111000000000000000001000 ,
b10000000000000000001100 &
b10000000000000000001100 )
b10000000000000000001100 -
b10000000000000000001000 %
b10000000000000000001000 (
b10000000000000000001000 +
b10000000000000000001000 1
1'
#92
0'
#93
b10000000000000000000000 #
b10000000000000000000000 .
1"
b10000000000000000000000 !
b10000000000000000000000 /
b10000000000000000000000 0
b1000000100000000000000000000 $
b1000000100000000000000000000 *
b1000000100000000000000000000 ,
b10000000000000000010000 &
b10000000000000000010000 )
b10000000000000000010000 -
b10000000000000000001100 %
b10000000000000000001100 (
b10000000000000000001100 +
b10000000000000000001100 1
1'
#94
0'
#95
b10000000000000010000 #
b10000000000000010000 .
b10000000000000000000100 !
b10000000000000000000100 /
b10000000000000000000100 0
0"
b100100000000100000000000000100 $
b100100000000100000000000000100 *
b100100000000100000000000000100 ,
b10000000000000000000100 &
b10000000000000000000100 )
b10000000000000000000100 -
b10000000000000000000000 %
b10000000000000000000000 (
b10000000000000000000000 +
b10000000000000000000000 1
1'
#96
0'
#97
b110000 #
b110000 .
b10000000000000000001000 !
b10000000000000000001000 /
b10000000000000000001000 0
b1100 $
b1100 *
b1100 ,
b10000000000000000001000 &
b10000000000000000001000 )
b10000000000000000001000 -
b10000000000000000000100 %
b10000000000000000000100 (
b10000000000000000000100 +
b10000000000000000000100 1
1'
#98
0'
#99
b11100000000000000000100000 #
b11100000000000000000100000 .
b10000000000000000001100 !
b10000000000000000001100 /
b10000000000000000001100 0
b11111000000000000000001000 $
b11111000000000000000001000 *
b11111000000000000000001000 ,
b10000000000000000001100 &
b10000000000000000001100 )
b10000000000000000001100 -
b10000000000000000001000 %
b10000000000000000001000 (
b10000000000000000001000 +
b10000000000000000001000 1
1'
#100
0'
#101
b10000000000000000000000 #
b10000000000000000000000 .
1"
b10000000000000000000000 !
b10000000000000000000000 /
b10000000000000000000000 0
b1000000100000000000000000000 $
b1000000100000000000000000000 *
b1000000100000000000000000000 ,
b10000000000000000010000 &
b10000000000000000010000 )
b10000000000000000010000 -
b10000000000000000001100 %
b10000000000000000001100 (
b10000000000000000001100 +
b10000000000000000001100 1
1'
#102
0'
#103
b10000000000000010000 #
b10000000000000010000 .
b10000000000000000000100 !
b10000000000000000000100 /
b10000000000000000000100 0
0"
b100100000000100000000000000100 $
b100100000000100000000000000100 *
b100100000000100000000000000100 ,
b10000000000000000000100 &
b10000000000000000000100 )
b10000000000000000000100 -
b10000000000000000000000 %
b10000000000000000000000 (
b10000000000000000000000 +
b10000000000000000000000 1
1'
#104
0'
#105
b110000 #
b110000 .
b10000000000000000001000 !
b10000000000000000001000 /
b10000000000000000001000 0
b1100 $
b1100 *
b1100 ,
b10000000000000000001000 &
b10000000000000000001000 )
b10000000000000000001000 -
b10000000000000000000100 %
b10000000000000000000100 (
b10000000000000000000100 +
b10000000000000000000100 1
1'
#106
0'
#107
b11100000000000000000100000 #
b11100000000000000000100000 .
b10000000000000000001100 !
b10000000000000000001100 /
b10000000000000000001100 0
b11111000000000000000001000 $
b11111000000000000000001000 *
b11111000000000000000001000 ,
b10000000000000000001100 &
b10000000000000000001100 )
b10000000000000000001100 -
b10000000000000000001000 %
b10000000000000000001000 (
b10000000000000000001000 +
b10000000000000000001000 1
1'
#108
0'
#109
b10000000000000000000000 #
b10000000000000000000000 .
1"
b10000000000000000000000 !
b10000000000000000000000 /
b10000000000000000000000 0
b1000000100000000000000000000 $
b1000000100000000000000000000 *
b1000000100000000000000000000 ,
b10000000000000000010000 &
b10000000000000000010000 )
b10000000000000000010000 -
b10000000000000000001100 %
b10000000000000000001100 (
b10000000000000000001100 +
b10000000000000000001100 1
1'
#110
0'
#111
b10000000000000010000 #
b10000000000000010000 .
b10000000000000000000100 !
b10000000000000000000100 /
b10000000000000000000100 0
0"
b100100000000100000000000000100 $
b100100000000100000000000000100 *
b100100000000100000000000000100 ,
b10000000000000000000100 &
b10000000000000000000100 )
b10000000000000000000100 -
b10000000000000000000000 %
b10000000000000000000000 (
b10000000000000000000000 +
b10000000000000000000000 1
1'
#112
0'
#113
b110000 #
b110000 .
b10000000000000000001000 !
b10000000000000000001000 /
b10000000000000000001000 0
b1100 $
b1100 *
b1100 ,
b10000000000000000001000 &
b10000000000000000001000 )
b10000000000000000001000 -
b10000000000000000000100 %
b10000000000000000000100 (
b10000000000000000000100 +
b10000000000000000000100 1
1'
#114
0'
#115
b11100000000000000000100000 #
b11100000000000000000100000 .
b10000000000000000001100 !
b10000000000000000001100 /
b10000000000000000001100 0
b11111000000000000000001000 $
b11111000000000000000001000 *
b11111000000000000000001000 ,
b10000000000000000001100 &
b10000000000000000001100 )
b10000000000000000001100 -
b10000000000000000001000 %
b10000000000000000001000 (
b10000000000000000001000 +
b10000000000000000001000 1
1'
#116
0'
#117
b10000000000000000000000 #
b10000000000000000000000 .
1"
b10000000000000000000000 !
b10000000000000000000000 /
b10000000000000000000000 0
b1000000100000000000000000000 $
b1000000100000000000000000000 *
b1000000100000000000000000000 ,
b10000000000000000010000 &
b10000000000000000010000 )
b10000000000000000010000 -
b10000000000000000001100 %
b10000000000000000001100 (
b10000000000000000001100 +
b10000000000000000001100 1
1'
#118
0'
#119
b10000000000000010000 #
b10000000000000010000 .
b10000000000000000000100 !
b10000000000000000000100 /
b10000000000000000000100 0
0"
b100100000000100000000000000100 $
b100100000000100000000000000100 *
b100100000000100000000000000100 ,
b10000000000000000000100 &
b10000000000000000000100 )
b10000000000000000000100 -
b10000000000000000000000 %
b10000000000000000000000 (
b10000000000000000000000 +
b10000000000000000000000 1
1'
#120
0'
#121
b110000 #
b110000 .
b10000000000000000001000 !
b10000000000000000001000 /
b10000000000000000001000 0
b1100 $
b1100 *
b1100 ,
b10000000000000000001000 &
b10000000000000000001000 )
b10000000000000000001000 -
b10000000000000000000100 %
b10000000000000000000100 (
b10000000000000000000100 +
b10000000000000000000100 1
1'
#122
0'
#123
b11100000000000000000100000 #
b11100000000000000000100000 .
b10000000000000000001100 !
b10000000000000000001100 /
b10000000000000000001100 0
b11111000000000000000001000 $
b11111000000000000000001000 *
b11111000000000000000001000 ,
b10000000000000000001100 &
b10000000000000000001100 )
b10000000000000000001100 -
b10000000000000000001000 %
b10000000000000000001000 (
b10000000000000000001000 +
b10000000000000000001000 1
1'
#124
0'
#125
b10000000000000000000000 #
b10000000000000000000000 .
1"
b10000000000000000000000 !
b10000000000000000000000 /
b10000000000000000000000 0
b1000000100000000000000000000 $
b1000000100000000000000000000 *
b1000000100000000000000000000 ,
b10000000000000000010000 &
b10000000000000000010000 )
b10000000000000000010000 -
b10000000000000000001100 %
b10000000000000000001100 (
b10000000000000000001100 +
b10000000000000000001100 1
1'
#126
0'
#127
b10000000000000010000 #
b10000000000000010000 .
b10000000000000000000100 !
b10000000000000000000100 /
b10000000000000000000100 0
0"
b100100000000100000000000000100 $
b100100000000100000000000000100 *
b100100000000100000000000000100 ,
b10000000000000000000100 &
b10000000000000000000100 )
b10000000000000000000100 -
b10000000000000000000000 %
b10000000000000000000000 (
b10000000000000000000000 +
b10000000000000000000000 1
1'
#128
0'
#129
b110000 #
b110000 .
b10000000000000000001000 !
b10000000000000000001000 /
b10000000000000000001000 0
b1100 $
b1100 *
b1100 ,
b10000000000000000001000 &
b10000000000000000001000 )
b10000000000000000001000 -
b10000000000000000000100 %
b10000000000000000000100 (
b10000000000000000000100 +
b10000000000000000000100 1
1'
#130
0'
#131
b11100000000000000000100000 #
b11100000000000000000100000 .
b10000000000000000001100 !
b10000000000000000001100 /
b10000000000000000001100 0
b11111000000000000000001000 $
b11111000000000000000001000 *
b11111000000000000000001000 ,
b10000000000000000001100 &
b10000000000000000001100 )
b10000000000000000001100 -
b10000000000000000001000 %
b10000000000000000001000 (
b10000000000000000001000 +
b10000000000000000001000 1
1'
#132
0'
#133
b10000000000000000000000 #
b10000000000000000000000 .
1"
b10000000000000000000000 !
b10000000000000000000000 /
b10000000000000000000000 0
b1000000100000000000000000000 $
b1000000100000000000000000000 *
b1000000100000000000000000000 ,
b10000000000000000010000 &
b10000000000000000010000 )
b10000000000000000010000 -
b10000000000000000001100 %
b10000000000000000001100 (
b10000000000000000001100 +
b10000000000000000001100 1
1'
#134
0'
#135
b10000000000000010000 #
b10000000000000010000 .
b10000000000000000000100 !
b10000000000000000000100 /
b10000000000000000000100 0
0"
b100100000000100000000000000100 $
b100100000000100000000000000100 *
b100100000000100000000000000100 ,
b10000000000000000000100 &
b10000000000000000000100 )
b10000000000000000000100 -
b10000000000000000000000 %
b10000000000000000000000 (
b10000000000000000000000 +
b10000000000000000000000 1
1'
#136
0'
